DMseg/DMseg.py
DMseg/__init__.py
DMseg-1.0.2.dist-info/LICENSE
DMseg-1.0.2.dist-info/METADATA
DMseg-1.0.2.dist-info/WHEEL
DMseg-1.0.2.dist-info/top_level.txt
DMseg-1.0.2.dist-info/RECORD
