Metadata-Version: 2.1
Name: DMseg
Version: 1.0.2
Summary: Python package for DMseg: detecting differential methylation regions in DNA methylome data
Author: James Dai, Kevin Wang
Author-email: <jdai@fredhutch.org>
License: MIT
Keywords: python,DNA methylation,Differentially methylated regions
Platform: UNKNOWN
Classifier: Topic :: Scientific/Engineering :: Bio-Informatics
License-File: LICENSE
Requires-Dist: pandas
Requires-Dist: numpy
